h0rn3t_sp1d3r/__init__.py
h0rn3t_sp1d3r/main.py
h0rn3t_sp1d3r-1.0.0.dist-info/licenses/LICENSE
h0rn3t_sp1d3r-1.0.0.dist-info/METADATA
h0rn3t_sp1d3r-1.0.0.dist-info/WHEEL
h0rn3t_sp1d3r-1.0.0.dist-info/top_level.txt
h0rn3t_sp1d3r-1.0.0.dist-info/RECORD
