Metadata-Version: 2.4
Name: h0rn3t_sp1d3r
Version: 1.0.0
Summary: A short description of your module
Home-page: https://github.com/H0rn3t-Sp1d3rs
Author: h0rn3t_sp1d3r
Author-email: tg@gmail.com
Classifier: Programming Language :: Python :: 3
Classifier: License :: OSI Approved :: MIT License
Classifier: Operating System :: OS Independent
Requires-Python: >=3.10
License-File: LICENSE
Requires-Dist: requests
Requires-Dist: colorama
Dynamic: author
Dynamic: author-email
Dynamic: classifier
Dynamic: description-content-type
Dynamic: home-page
Dynamic: license-file
Dynamic: requires-dist
Dynamic: requires-python
Dynamic: summary
